adminribbon/__init__.py
adminribbon/context_processors.py
adminribbon/templates/admin/base_site.html
django_admin_ribbon-0.1.8.dist-info/LICENSE
django_admin_ribbon-0.1.8.dist-info/METADATA
django_admin_ribbon-0.1.8.dist-info/WHEEL
django_admin_ribbon-0.1.8.dist-info/top_level.txt
django_admin_ribbon-0.1.8.dist-info/RECORD
