Metadata-Version: 2.1
Name: django-admin-ribbon
Version: 0.1.8
Summary: Quickly differentiate django environments
Home-page: https://github.com/skioo/django-admin-ribbon
Author: Nicholas Wolff
Author-email: nwolff@gmail.com
License: MIT
Download-URL: https://pypi.python.org/pypi/django-admin-ribbon
Platform: UNKNOWN
Classifier: Development Status :: 5 - Production/Stable
Classifier: Environment :: Web Environment
Classifier: Framework :: Django
Classifier: Intended Audience :: Developers
Classifier: License :: OSI Approved :: BSD License
Classifier: Operating System :: OS Independent
Classifier: Programming Language :: Python
Classifier: Programming Language :: Python :: 3.5
Classifier: Programming Language :: Python :: 3.6
Classifier: Programming Language :: Python :: 3.7
Classifier: Programming Language :: Python :: 3.8
Requires-Dist: Django (>=1.8)
